[
    {
        "title": "机场推荐与机场评测",
        "icon": "机场推荐与机场评测_icon.webp",
        "url": "https://jichangtuijian.com",
        "description": "深度聚合网络协议相关的前沿资讯与技术评测，通过系统化的选型建议与数据反馈，助力用户构建稳定可靠的互联环境",
        "category": "跨境互联"
    },
    {
        "title": "润土分享",
        "icon": "润土分享_icon.webp",
        "url": "https://runtushare.net",
        "description": "知名的前沿技术分享平台，深度聚焦数字化生存解决方案，提供详尽的海外服务订阅教程与科学的网络环境配置指南",
        "category": "跨境互联"
    },
    {
        "title": "一个朋友",
        "icon": "一个朋友_icon.webp",
        "url": "https://ygpy.net",
        "description": "跨境出海工具导航站，涵盖机场推荐、软件列表和网址导航等内容，致力于解决用户上网难题，是探索互联网的第一站",
        "category": "跨境互联"
    },
    {
        "title": "科学上网",
        "icon": "科学上网_icon.webp",
        "url": "https://www.zoio.net",
        "description": "",
        "category": "跨境互联"
    }
]